tidypolars/__init__.py
tidypolars/funs.py
tidypolars/lubridate.py
tidypolars/reexports.py
tidypolars/stringr.py
tidypolars/tibble_df.py
tidypolars/tidyselect.py
tidypolars/utils.py
tidypolars-0.3.2.dist-info/LICENSE
tidypolars-0.3.2.dist-info/METADATA
tidypolars-0.3.2.dist-info/WHEEL
tidypolars-0.3.2.dist-info/RECORD
