Metadata-Version: 2.1
Name: tidypolars
Version: 0.3.2
Summary: Tidy interface to polars
License: MIT
Author: Mark Fairbanks
Requires-Python: >=3.10,<3.12
Classifier: License :: OSI Approved :: MIT License
Classifier: Programming Language :: Python :: 3
Classifier: Programming Language :: Python :: 3.10
Classifier: Programming Language :: Python :: 3.11
Requires-Dist: numpy (>=1.16.0)
Requires-Dist: polars (>=1.0.0)
